msf/__init__.py
msf/driver.py
msf/conf/__init__.py
msf/conf/workflow_conf.py
msf/core/__init__.py
msf/core/core.py
msf/engine/__init__.py
msf/engine/engine.py
msf/engine/utils.py
msf/utils/__init__.py
msf/utils/import_utils.py
msf-0.2.0.dist-info/LICENSE
msf-0.2.0.dist-info/METADATA
msf-0.2.0.dist-info/WHEEL
msf-0.2.0.dist-info/top_level.txt
msf-0.2.0.dist-info/RECORD
