Metadata-Version: 2.1
Name: msf
Version: 0.2.0
Summary: python easy microservices framework
Home-page: https://github.com/EeyoreLee/microservices-framework
Author: EeyoreLee
Author-email: li.chunyu0412@outlook.com
License: UNKNOWN
Platform: UNKNOWN
Classifier: Programming Language :: Python :: 3
Classifier: License :: OSI Approved :: MIT License
Classifier: Operating System :: OS Independent
Requires-Python: >=3.6
License-File: LICENSE
Requires-Dist: flask
